LICENSE
README.md
heir_play/__init__.py
heir_play/heir_opt.py
heir_play/utils.py
heir_play-0.0.4.dist-info/METADATA
heir_play-0.0.4.dist-info/WHEEL
heir_play-0.0.4.dist-info/licenses/LICENSE
heir_play-0.0.4.dist-info/RECORD
