Metadata-Version: 2.3
Name: heir_play
Version: 0.0.4
Summary: A cell magic enabling one to run HEIR pipelines in Jupyter notebooks.
Project-URL: Homepage, https://github.com/google/heir
Project-URL: Issues, https://github.com/google/heir/issues
Author-email: Jeremy Kun <jkun@google.com>, Asra Ali <asraa@google.com>
Classifier: Framework :: Jupyter
Classifier: Intended Audience :: Developers
Classifier: License :: OSI Approved :: Apache Software License
Classifier: Topic :: Security :: Cryptography
Classifier: Topic :: Software Development :: Compilers
Requires-Python: >=3.8
Requires-Dist: ipython>=7.34.0
